composabl_train/main.cpython-310-x86_64-linux-gnu.so
composabl_train/__init__.cpython-310-x86_64-linux-gnu.so
composabl_train/trainer/skill_trainer_coordinated_set.cpython-310-x86_64-linux-gnu.so
composabl_train/trainer/skill_trainer_coordinated_population.cpython-310-x86_64-linux-gnu.so
composabl_train/trainer/skill_trainer_base.cpython-310-x86_64-linux-gnu.so
composabl_train/trainer/composabl_ppo.cpython-310-x86_64-linux-gnu.so
composabl_train/trainer/training_callbacks.cpython-310-x86_64-linux-gnu.so
composabl_train/trainer/trainer.cpython-310-x86_64-linux-gnu.so
composabl_train/trainer/__init__.cpython-310-x86_64-linux-gnu.so
composabl_train/trainer/create_skill_trainer.cpython-310-x86_64-linux-gnu.so
composabl_train/trainer/algorithm_config.cpython-310-x86_64-linux-gnu.so
composabl_train/trainer/skill_trainer.cpython-310-x86_64-linux-gnu.so
composabl_train/env/env_composabl_multi_agent.cpython-310-x86_64-linux-gnu.so
composabl_train/env/__init__.cpython-310-x86_64-linux-gnu.so
composabl_train/env/env_mgr.cpython-310-x86_64-linux-gnu.so
composabl_train/env/env_composabl.cpython-310-x86_64-linux-gnu.so
composabl_train/model/skill_model.cpython-310-x86_64-linux-gnu.so
composabl_train/model/skill_model_coordinated.cpython-310-x86_64-linux-gnu.so
composabl_train/model/__init__.cpython-310-x86_64-linux-gnu.so
composabl_train/utils/validate_util.cpython-310-x86_64-linux-gnu.so
composabl_train/utils/onnx_helper.cpython-310-x86_64-linux-gnu.so
composabl_train/utils/env_validator.cpython-310-x86_64-linux-gnu.so
composabl_train/utils/__init__.cpython-310-x86_64-linux-gnu.so
composabl_train/actor/sim_mgr_actor.cpython-310-x86_64-linux-gnu.so
composabl_train/actor/__init__.cpython-310-x86_64-linux-gnu.so
composabl_train/actor/actor.cpython-310-x86_64-linux-gnu.so
composabl_train/actor/metrics_actor.cpython-310-x86_64-linux-gnu.so
composabl_train/skill_processors/skill_selector_processor.cpython-310-x86_64-linux-gnu.so
composabl_train_dev-0.19.1.dist-info/WHEEL
composabl_train_dev-0.19.1.dist-info/top_level.txt
composabl_train_dev-0.19.1.dist-info/METADATA
composabl_train_dev-0.19.1.dist-info/RECORD
